ilabs.s3util-0.6.7-py3.5-nspkg.pth
ilabs/s3util/__init__.py
ilabs/s3util/command.py
ilabs/s3util/main_pypi.py
ilabs/s3util/main_upload.py
ilabs/s3util/util.py
ilabs.s3util-0.6.7.dist-info/DESCRIPTION.rst
ilabs.s3util-0.6.7.dist-info/LICENSE.txt
ilabs.s3util-0.6.7.dist-info/METADATA
ilabs.s3util-0.6.7.dist-info/RECORD
ilabs.s3util-0.6.7.dist-info/WHEEL
ilabs.s3util-0.6.7.dist-info/entry_points.txt
ilabs.s3util-0.6.7.dist-info/metadata.json
ilabs.s3util-0.6.7.dist-info/namespace_packages.txt
ilabs.s3util-0.6.7.dist-info/top_level.txt
