Metadata-Version: 2.0
Name: ilabs.s3util
Version: 0.6.7
Summary: Utilities to support simple private PyPI on Amazon S3
Home-page: https://github.com/innodatalabs/ilabs.s3util
Author: Mike Kroutikov
Author-email: mkroutikov@innodata.com
License: MIT
Keywords: s3 setup pypi pip
Platform: UNKNOWN
Classifier: Development Status :: 4 - Beta
Classifier: Intended Audience :: Developers
Classifier: License :: OSI Approved :: MIT License
Classifier: Programming Language :: Python :: 3
Classifier: Programming Language :: Python :: 3.3
Classifier: Programming Language :: Python :: 3.4
Classifier: Programming Language :: Python :: 3.5
Classifier: Programming Language :: Python :: 3.6
Classifier: Programming Language :: Python :: Implementation :: CPython
Classifier: Programming Language :: Python :: Implementation :: PyPy
Classifier: Topic :: Software Development :: Libraries :: Python Modules
Requires-Dist: boto3
